pycroscopy/__init__.py
pycroscopy/__version__.py
pycroscopy/corr/__init__.py
pycroscopy/fft/__init__.py
pycroscopy/fft/image_fft.py
pycroscopy/image/__init__.py
pycroscopy/image/image_atoms.py
pycroscopy/image/image_clean.py
pycroscopy/image/image_graph.py
pycroscopy/image/image_registration.py
pycroscopy/image/image_utilities.py
pycroscopy/image/image_window.py
pycroscopy/learn/__init__.py
pycroscopy/learn/dl/__init__.py
pycroscopy/learn/dl/datautils.py
pycroscopy/learn/dl/models.py
pycroscopy/learn/dl/nnblocks.py
pycroscopy/learn/dl/trainer.py
pycroscopy/learn/ml/__init__.py
pycroscopy/learn/ml/decompose.py
pycroscopy/learn/ml/matrix_factor.py
pycroscopy/signal/__init__.py
pycroscopy/stats/__init__.py
pycroscopy/stats/atom_stats.py
pycroscopy/stats/atom_stats_n.py
pycroscopy/stats/tree.py
pycroscopy/viz/__init__.py
pycroscopy-0.63.3.dist-info/LICENSE.txt
pycroscopy-0.63.3.dist-info/METADATA
pycroscopy-0.63.3.dist-info/WHEEL
pycroscopy-0.63.3.dist-info/top_level.txt
pycroscopy-0.63.3.dist-info/RECORD
