Metadata-Version: 2.1
Name: pycroscopy
Version: 0.63.3
Summary: Python library for scientific analysis of microscopy data
Home-page: https://pycroscopy.github.io/pycroscopy/about.html
Author: Pycroscopy contributors
Author-email: pycroscopy@gmail.com
License: MIT
Keywords: EELS,STEM,TEM,XRD,AFM,SPM,STS,band excitation,BE,BEPS,Raman,NanoIR,electron microscopy, scanning probe, x-rays,atomic force microscopy,SIMS,energy,spectroscopy,imaging,microscopy,spectracharacterization,spectrogram,hyperspectral,multidimensional,data format,universal,clustering,decomposition,curve fitting,data analysis,PCA, SVD, NMF, DBSCAN, kMeans,machine learning,bayesian inference,fft filtering,signal processing,image cleaning,denoising,model,msa,quantification
Platform: Linux
Platform: Mac OSX
Platform: Windows 10/8.1/8/7
Classifier: Development Status :: 3 - Alpha
Classifier: Environment :: Console
Classifier: Intended Audience :: Science/Research
Classifier: License :: OSI Approved :: MIT License
Classifier: Natural Language :: English
Classifier: Operating System :: OS Independent
Classifier: Programming Language :: Cython
Classifier: Programming Language :: Python :: 3
Classifier: Programming Language :: Python :: 3.5
Classifier: Programming Language :: Python :: 3.6
Classifier: Programming Language :: Python :: 3.7
Classifier: Programming Language :: Python :: Implementation :: CPython
Classifier: Topic :: Scientific/Engineering :: Chemistry
Classifier: Topic :: Scientific/Engineering :: Physics
Classifier: Topic :: Scientific/Engineering :: Information Analysis
License-File: LICENSE.txt
Requires-Dist: numpy >=1.13.0
Requires-Dist: scipy <1.10.2,>=0.17
Requires-Dist: scikit-image >=0.12.3
Requires-Dist: scikit-learn >=0.17.1
Requires-Dist: matplotlib >=2.0.0
Requires-Dist: torch >=1.0.0
Requires-Dist: tensorly >=0.6.0
Requires-Dist: tqdm
Requires-Dist: ipywidgets >=5.2.2
Requires-Dist: ipython
Requires-Dist: simpleitk
Requires-Dist: sidpy >=0.12.1
Requires-Dist: pysptools
Requires-Dist: cvxopt >=1.2.7
Requires-Dist: SciFiReaders >=0.10.0
Requires-Dist: pywget
Requires-Dist: pyTEMlib >=0.2023.8.0
Requires-Dist: ipympl
